README.md
setup.py
pulumi_hcp/__init__.py
pulumi_hcp/_inputs.py
pulumi_hcp/_utilities.py
pulumi_hcp/aws_network_peering.py
pulumi_hcp/aws_transit_gateway_attachment.py
pulumi_hcp/azure_peering_connection.py
pulumi_hcp/boundary_cluster.py
pulumi_hcp/consul_cluster.py
pulumi_hcp/consul_cluster_root_token.py
pulumi_hcp/consul_snapshot.py
pulumi_hcp/get_aws_network_peering.py
pulumi_hcp/get_aws_transit_gateway_attachment.py
pulumi_hcp/get_azure_peering_connection.py
pulumi_hcp/get_boundary_cluster.py
pulumi_hcp/get_consul_agent_helm_config.py
pulumi_hcp/get_consul_agent_kubernetes_secret.py
pulumi_hcp/get_consul_cluster.py
pulumi_hcp/get_consul_versions.py
pulumi_hcp/get_hvn.py
pulumi_hcp/get_hvn_peering_connection.py
pulumi_hcp/get_hvn_route.py
pulumi_hcp/get_packer_image.py
pulumi_hcp/get_packer_image_iteration.py
pulumi_hcp/get_packer_iteration.py
pulumi_hcp/get_vault_cluster.py
pulumi_hcp/hvn.py
pulumi_hcp/hvn_peering_connection.py
pulumi_hcp/hvn_route.py
pulumi_hcp/outputs.py
pulumi_hcp/provider.py
pulumi_hcp/pulumi-plugin.json
pulumi_hcp/py.typed
pulumi_hcp/vault_cluster.py
pulumi_hcp/vault_cluster_admin_token.py
pulumi_hcp.egg-info/PKG-INFO
pulumi_hcp.egg-info/SOURCES.txt
pulumi_hcp.egg-info/dependency_links.txt
pulumi_hcp.egg-info/not-zip-safe
pulumi_hcp.egg-info/requires.txt
pulumi_hcp.egg-info/top_level.txt
pulumi_hcp/config/__init__.py
pulumi_hcp/config/vars.py