Metadata-Version: 2.1
Name: pulumi-hcp
Version: 0.1.14
Summary: A Pulumi package for creating and managing HCP cloud resources.
Home-page: https://pulumi.io
License: Apache-2.0
Project-URL: Repository, https://github.com/grapl-security/pulumi-hcp
Keywords: pulumi hcp category/infrastructure
Platform: UNKNOWN
